_init_/__init__.py
ytmp3-3.2.4.dist-info/METADATA
ytmp3-3.2.4.dist-info/WHEEL
ytmp3-3.2.4.dist-info/top_level.txt
ytmp3-3.2.4.dist-info/RECORD
